Metadata-Version: 2.1
Name: deFit
Version: 0.3.0
Summary: Fitting Differential Equations to Time Series Data
Home-page: https://github.com/yueqinhu/defit
Author: Yueqin Hu, Qingshan Liu, Minglan Li
Author-email: yueqinhu@bnu.edu.cn, liuqingshan@mail.bnu.edu.cn, 202431061029@mail.bnu.edu.cn
License: GPL-3
Project-URL: Documentation, https://github.com/yueqinhu/defit
Project-URL: Source Code, https://github.com/yueqinhu/defit
Keywords: ODE,optimization,numerical methods,Intensive longitudinal data,dynamical system,differential equation,time series
Classifier: Programming Language :: Python :: 3
Classifier: License :: OSI Approved :: GNU General Public License v3 (GPLv3)
Classifier: Operating System :: OS Independent
Requires-Python: >=3.7
Requires-Dist: pandas
Requires-Dist: scipy
Requires-Dist: numpy
Requires-Dist: pathlib
Requires-Dist: matplotlib
Requires-Dist: importlib-metadata ; python_version == "3.8"
